vr900_connector-0.0.26.dist-info/DESCRIPTION.rst
vr900_connector-0.0.26.dist-info/METADATA
vr900_connector-0.0.26.dist-info/RECORD
vr900_connector-0.0.26.dist-info/WHEEL
vr900_connector-0.0.26.dist-info/metadata.json
vr900_connector-0.0.26.dist-info/top_level.txt
vr900connector/__init__.py
vr900connector/print_responses.py
vr900connector/print_system.py
vr900connector/vaillantsystemmanager.py
vr900connector/api/__init__.py
vr900connector/api/apiconnector.py
vr900connector/api/apierror.py
vr900connector/api/constant.py
vr900connector/model/__init__.py
vr900connector/model/activemode.py
vr900connector/model/boilerstatus.py
vr900connector/model/boostmode.py
vr900connector/model/circulation.py
vr900connector/model/component.py
vr900connector/model/constant.py
vr900connector/model/device.py
vr900connector/model/holidaymode.py
vr900connector/model/hotwater.py
vr900connector/model/mapper.py
vr900connector/model/quickmode.py
vr900connector/model/quickveto.py
vr900connector/model/room.py
vr900connector/model/system.py
vr900connector/model/timeprogram.py
vr900connector/model/zone.py
vr900connector/util/__init__.py
vr900connector/util/fileutils.py
