Metadata-Version: 2.0
Name: vr900-connector
Version: 0.0.26
Summary: Connector to handle vaillant vr900/vr920 data
Home-page: https://github.com/thomasgermain/vr900-connector.git
Author: Thomas Germain
Author-email: thomas.germain@live.be
License: MIT
Platform: UNKNOWN
Requires-Dist: requests
Requires-Dist: responses
Requires-Dist: pytest
